scaffold_generator/__init__.py
scaffold_generator/admin.py
scaffold_generator/apps.py
scaffold_generator/defaults.py
scaffold_generator/fields.py
scaffold_generator/models.py
scaffold_generator/scaffold.py
scaffold_generator/settings.py
scaffold_generator/tests.py
scaffold_generator/utils.py
scaffold_generator/views.py
scaffold_generator/management/__init__.py
scaffold_generator/management/commands/__init__.py
scaffold_generator/management/commands/generatescaffold.py
scaffold_generator/migrations/__init__.py
scaffold_generator/templates/scaffold_generator/admin.py.template
scaffold_generator/templates/scaffold_generator/forms.py.template
scaffold_generator/templates/scaffold_generator/models.py.template
scaffold_generator/templates/scaffold_generator/urls.py.default.template
scaffold_generator/templates/scaffold_generator/urls.py.template
scaffold_generator/templates/scaffold_generator/views.py.template
scaffold_generator/templates/scaffold_generator/api/serializers.py.template
scaffold_generator/templates/scaffold_generator/api/urls.py.default.template
scaffold_generator/templates/scaffold_generator/api/urls.py.template
scaffold_generator/templates/scaffold_generator/api/views.py.template
scaffold_generator/templates/scaffold_generator/components/render_import.template
scaffold_generator/templatetags/__init__.py
scaffold_generator/templatetags/scaffold_generator_helper.py
django_scaffold_generator-0.0.1.dist-info/LICENSE.txt
django_scaffold_generator-0.0.1.dist-info/METADATA
django_scaffold_generator-0.0.1.dist-info/WHEEL
django_scaffold_generator-0.0.1.dist-info/top_level.txt
django_scaffold_generator-0.0.1.dist-info/RECORD
