Metadata-Version: 2.1
Name: django-scaffold-generator
Version: 0.0.1
Summary: Ruby on Rails like Scaffolding Provider for Django
Home-page: https://github.com/iamswaroopp/django-scaffold-generator
Download-URL: https://github.com/iamswaroopp/django-scaffold-generator/archive/0.0.1.zip
Author: Swaroop P
Author-email: iamswaroopp@gmail.com
License: mit
Project-URL: Bug Reports, https://github.com/iamswaroopp/django-scaffold-generator/issues
Keywords: django,developement,scaffold_generator,startapp,rapid,rad,rapid application developmentpython
Classifier: Development Status :: 4 - Beta
Classifier: Intended Audience :: Developers
Classifier: Topic :: Software Development :: Libraries
Classifier: Topic :: Software Development :: Libraries :: Application Frameworks
Classifier: License :: OSI Approved :: MIT License
Classifier: Framework :: Django
Classifier: Programming Language :: Python :: 3
Classifier: Programming Language :: Python :: 3.8
Classifier: Programming Language :: Python :: 3.9
Classifier: Programming Language :: Python :: 3.10
Classifier: Programming Language :: Python :: 3.11
Classifier: Programming Language :: Python :: 3.12
Requires-Python: >=3.6
License-File: LICENSE.txt
Requires-Dist: django
